dragoon/__init__.py
dragoon/dragoon.py
dragoon-0.0.2.dist-info/entry_points.txt
dragoon-0.0.2.dist-info/LICENSE
dragoon-0.0.2.dist-info/WHEEL
dragoon-0.0.2.dist-info/METADATA
dragoon-0.0.2.dist-info/RECORD
