Metadata-Version: 2.1
Name: dragoon
Version: 0.0.2
Summary: Automate Dragoon Rolls
Home-page: https://github.com/juanrgon/dragoon
License: UNKNOWN
Author: Juan Gonzalez
Author-email: jrg2156@gmail.com
Classifier: License :: OSI Approved :: MIT License
